boxprint/__init__.py
boxprint/bprint.py
boxprint/dprint.py
boxprint/stprint.py
pybox/__init__.py
boxprint-0.0.15.dist-info/LICENSE
boxprint-0.0.15.dist-info/METADATA
boxprint-0.0.15.dist-info/WHEEL
boxprint-0.0.15.dist-info/top_level.txt
boxprint-0.0.15.dist-info/RECORD
